miSRA/README.md
miSRA/__init__.py
miSRA/miSRA.py
miSRA/example_configs/annotated_miSRA_example_config.json
miSRA/example_configs/miSRA_example_config.json
misra-0.0.3.dist-info/entry_points.txt
misra-0.0.3.dist-info/WHEEL
misra-0.0.3.dist-info/METADATA
misra-0.0.3.dist-info/RECORD
